ata_models/__init__.py
ata_models/helpers.py
ata_models/init_db.py
ata_models/models.py
ata_models-0.0.1.dist-info/LICENSE
ata_models-0.0.1.dist-info/WHEEL
ata_models-0.0.1.dist-info/METADATA
ata_models-0.0.1.dist-info/RECORD
